poppy_inverse_kinematics/__init__.py
poppy_inverse_kinematics/creature.py
poppy_inverse_kinematics/creature_interface.py
poppy_inverse_kinematics/forward_kinematics.py
poppy_inverse_kinematics/inverse_kinematic.py
poppy_inverse_kinematics/meta_creature.py
poppy_inverse_kinematics/meta_model.py
poppy_inverse_kinematics/model.py
poppy_inverse_kinematics/model_config.py
poppy_inverse_kinematics/model_interface.py
poppy_inverse_kinematics/plot_utils.py
poppy_inverse_kinematics/robot_utils.py
poppy_inverse_kinematics/test_sets.py
poppy_inverse_kinematics/resources/Poppy_Torso.URDF
poppy_inverse_kinematics/resources/__init__.py
poppy_inverse_kinematics/resources/__init__.pyc
poppy_inverse_kinematics/resources/poppy_ergo.URDF
poppy_inverse_kinematics-1.3.1.dist-info/DESCRIPTION.rst
poppy_inverse_kinematics-1.3.1.dist-info/METADATA
poppy_inverse_kinematics-1.3.1.dist-info/RECORD
poppy_inverse_kinematics-1.3.1.dist-info/WHEEL
poppy_inverse_kinematics-1.3.1.dist-info/metadata.json
poppy_inverse_kinematics-1.3.1.dist-info/top_level.txt
