Metadata-Version: 2.0
Name: poppy-inverse-kinematics
Version: 1.3.1
Summary: An inverse kinematics library aiming performance and modularity
Home-page: https://github.com/Phylliade/poppy-inverse-kinematics
Author: Pierre Manceron
Author-email: UNKNOWN
License: GNU GENERAL PUBLIC LICENSE Version 3
Platform: UNKNOWN
Requires-Dist: numpy
Requires-Dist: scipy
Requires-Dist: sympy
